EasyTransformer/bert.py
EasyTransformer/transformer.py
EasyTransformer-0.0.1.dist-info/METADATA
EasyTransformer-0.0.1.dist-info/WHEEL
EasyTransformer-0.0.1.dist-info/top_level.txt
EasyTransformer-0.0.1.dist-info/RECORD
