Metadata-Version: 2.1
Name: EasyTransformer
Version: 0.0.1
Summary: Simple implement of BERT and Transformer extracted from other repo
Home-page: https://github.com/Ricardokevins
Author: kevinpro
Author-email: 3121416933@qq.com
License: UNKNOWN
Platform: UNKNOWN
Requires-Dist: numpy
Requires-Dist: torch
